rclone/__init__.py
rclone/client.py
rclone/exceptions.py
rclone/models.py
rclone/parser.py
rclone/process.py
rclone/py.typed
rclone/util.py
rclone/_generated/__init__.py
rclone/_generated/check_commands.py
rclone/_generated/common.py
rclone/_generated/config_commands.py
rclone/_generated/listing_commands.py
rclone/_generated/serve_commands.py
rclone/_generated/sync_commands.py
rclone/_generated/utility_commands.py
rclone/bin/rclone-linux-amd64
rclone_adapter-0.2.0.dist-info/licenses/LICENSE
rclone_adapter-0.2.0.dist-info/METADATA
rclone_adapter-0.2.0.dist-info/WHEEL
rclone_adapter-0.2.0.dist-info/top_level.txt
rclone_adapter-0.2.0.dist-info/RECORD
