Metadata-Version: 2.4
Name: rclone-adapter
Version: 0.2.0
Summary: Modern async Python wrapper for rclone
Author-email: Dirk Petersen <dp@nowhere.com>
License: MIT
Project-URL: Homepage, https://github.com/dirkpetersen/rclone-adapter
Project-URL: Repository, https://github.com/dirkpetersen/rclone-adapter
Project-URL: Issues, https://github.com/dirkpetersen/rclone-adapter/issues
Project-URL: Documentation, https://github.com/dirkpetersen/rclone-adapter/blob/main/README.md
Keywords: rclone,cloud,storage,async,s3,backup
Classifier: Development Status :: 3 - Alpha
Classifier: Intended Audience :: Developers
Classifier: Intended Audience :: System Administrators
Classifier: Topic :: System :: Archiving
Classifier: Topic :: System :: Filesystems
Classifier: License :: OSI Approved :: MIT License
Classifier: Programming Language :: Python :: 3
Classifier: Programming Language :: Python :: 3.10
Classifier: Programming Language :: Python :: 3.11
Classifier: Programming Language :: Python :: 3.12
Classifier: Programming Language :: Python :: 3.13
Classifier: Programming Language :: Python :: 3.14
Classifier: Programming Language :: Python :: Implementation :: CPython
Classifier: Framework :: AsyncIO
Requires-Python: >=3.10
License-File: LICENSE
Requires-Dist: pydantic<3.0,>=2.0
Requires-Dist: rich<14.0,>=13.0
Requires-Dist: structlog<25.0,>=24.0
Provides-Extra: api
Requires-Dist: fastapi<1.0,>=0.110; extra == "api"
Requires-Dist: rq<2.0,>=1.16; extra == "api"
Requires-Dist: redis<6.0,>=5.0; extra == "api"
Requires-Dist: uvicorn<1.0,>=0.27; extra == "api"
Provides-Extra: dev
Requires-Dist: pytest<9.0,>=8.0; extra == "dev"
Requires-Dist: pytest-asyncio<1.0,>=0.23; extra == "dev"
Requires-Dist: pytest-cov<5.0,>=4.1; extra == "dev"
Requires-Dist: mypy<2.0,>=1.8; extra == "dev"
Requires-Dist: ruff<1.0,>=0.2; extra == "dev"
Requires-Dist: freezegun<2.0,>=1.4; extra == "dev"
Requires-Dist: fakeredis<3.0,>=2.21; extra == "dev"
Dynamic: license-file
